cpprb-11.0.0.dist-info/WHEEL
cpprb-11.0.0.dist-info/LICENSE
cpprb-11.0.0.dist-info/top_level.txt
cpprb-11.0.0.dist-info/RECORD
cpprb-11.0.0.dist-info/METADATA
cpprb/multiprocessing.py
cpprb/__init__.py
cpprb/PyReplayBuffer.cpython-38-aarch64-linux-gnu.so
cpprb/util.py
cpprb/HER.py
cpprb/VectorWrapper.cpython-38-aarch64-linux-gnu.so
cpprb/LaBER.py
